README.rst
setup.py
careful_requests/__init__.py
careful_requests/careful_requests.py
careful_requests/more_careful.py
careful_requests/utils.py
careful_requests.egg-info/PKG-INFO
careful_requests.egg-info/SOURCES.txt
careful_requests.egg-info/dependency_links.txt
careful_requests.egg-info/not-zip-safe
careful_requests.egg-info/requires.txt
careful_requests.egg-info/top_level.txt